django_log/__init__.py
django_log/middleware/__init__.py
django_log/middleware/log.py
django_log-0.0.3.dist-info/LICENSE
django_log-0.0.3.dist-info/METADATA
django_log-0.0.3.dist-info/WHEEL
django_log-0.0.3.dist-info/top_level.txt
django_log-0.0.3.dist-info/RECORD
