Metadata-Version: 2.1
Name: django-log
Version: 0.0.3
Summary: Log request, response and erros in file
Home-page: https://github.com/mandala21/django_log
Author: Lucas Resende
Author-email: lucasresone@gmail.com
License: UNKNOWN
Platform: UNKNOWN
Classifier: Programming Language :: Python :: 3
Classifier: License :: OSI Approved :: MIT License
Classifier: Operating System :: OS Independent
